timeflies.py
timeflies-0.0.1.dist-info/DESCRIPTION.rst
timeflies-0.0.1.dist-info/METADATA
timeflies-0.0.1.dist-info/RECORD
timeflies-0.0.1.dist-info/WHEEL
timeflies-0.0.1.dist-info/metadata.json
timeflies-0.0.1.dist-info/top_level.txt
